pylade/__init__.py
pylade/allowed_classes.py
pylade/console_scripts/__init__.py
pylade/console_scripts/args_parsers/__init__.py
pylade/console_scripts/args_parsers/detect_script_args_parser.py
pylade/console_scripts/args_parsers/evaluate_script_args_parser.py
pylade/console_scripts/args_parsers/train_script_args_parser.py
pylade/console_scripts/detect.py
pylade/console_scripts/evaluate.py
pylade/console_scripts/train.py
pylade/corpus_readers/__init__.py
pylade/corpus_readers/corpus_reader.py
pylade/corpus_readers/csv_corpus_reader.py
pylade/corpus_readers/twitter_corpus_reader.py
pylade/data/model.json
pylade/implementations/__init__.py
pylade/implementations/cavnar_trenkle_impl.py
pylade/implementations/implementation.py
pylade/utils.py
pylade-0.3.0.dist-info/LICENSE.md
pylade-0.3.0.dist-info/WHEEL
pylade-0.3.0.dist-info/entry_points.txt
pylade-0.3.0.dist-info/METADATA
pylade-0.3.0.dist-info/RECORD
