Metadata-Version: 2.1
Name: pylade
Version: 0.3.0
Summary: PyLaDe - Language Detection tool written in Python.
Home-page: https://github.com/fievelk/pylade
License: MIT
Author: Pierpaolo Pantone
Author-email: 24alsecondo@gmail.com
Requires-Python: >=3.8,<=3.12
Classifier: License :: OSI Approved :: MIT License
Classifier: Programming Language :: Python :: 3
Classifier: Programming Language :: Python :: 3.8
Classifier: Programming Language :: Python :: 3.9
Classifier: Programming Language :: Python :: 3.10
Classifier: Programming Language :: Python :: 3.11
Requires-Dist: nltk (>=3.8.1,<4.0.0)
Project-URL: Repository, https://github.com/fievelk/pylade
